{
    "statistics": [
        {
            "x": "2021-12-02T06:53:10Z",
            "F": 73,
            "M": 686,
            "FX": 0,
            "MX": 0,
            "X": 0,
            "NB": 0,
            "+": 1,
            "?": 0,
            "-": 4810
        },
        {
            "x": "2021-11-02T06:52:28Z",
            "F": 73,
            "M": 685,
            "FX": 0,
            "MX": 0,
            "X": 0,
            "NB": 0,
            "+": 1,
            "?": 0,
            "-": 4805
        },
        {
            "x": "2022-02-02T06:54:45Z",
            "F": 72,
            "M": 685,
            "FX": 0,
            "MX": 0,
            "X": 0,
            "NB": 0,
            "+": 1,
            "?": 0,
            "-": 4832
        },
        {
            "x": "2022-01-02T06:57:28Z",
            "F": 72,
            "M": 685,
            "FX": 0,
            "MX": 0,
            "X": 0,
            "NB": 0,
            "+": 1,
            "?": 0,
            "-": 4827
        },
        {
            "x": "2021-10-02T06:53:55Z",
            "F": 65,
            "M": 633,
            "FX": 0,
            "MX": 0,
            "X": 0,
            "NB": 0,
            "+": 1,
            "?": 0,
            "-": 4858
        },
        {
            "x": "2021-09-23T07:15:14Z",
            "F": 65,
            "M": 633,
            "FX": 0,
            "MX": 0,
            "X": 0,
            "NB": 0,
            "+": 1,
            "?": 0,
            "-": 4855
        },
        {
            "x": "2021-09-09T07:15:30Z",
            "F": 54,
            "M": 496,
            "FX": 0,
            "MX": 0,
            "X": 0,
            "NB": 0,
            "+": 1,
            "?": 0,
            "-": 4999
        },
        {
            "x": "2021-09-02T07:15:55Z",
            "F": 54,
            "M": 495,
            "FX": 0,
            "MX": 0,
            "X": 0,
            "NB": 0,
            "+": 1,
            "?": 0,
            "-": 4992
        },
        {
            "x": "2021-08-26T07:12:23Z",
            "F": 19,
            "M": 242,
            "FX": 0,
            "MX": 0,
            "X": 0,
            "NB": 0,
            "+": 1,
            "?": 0,
            "-": 5270
        },
        {
            "x": "2021-08-19T07:10:11Z",
            "F": 6,
            "M": 80,
            "FX": 0,
            "MX": 0,
            "X": 0,
            "NB": 0,
            "+": 1,
            "?": 0,
            "-": 5446
        },
        {
            "x": "2021-08-16T15:40:13Z",
            "F": 5,
            "M": 61,
            "FX": 0,
            "MX": 0,
            "X": 0,
            "NB": 0,
            "+": 1,
            "?": 0,
            "-": 5466
        },
        {
            "x": "2021-08-15T16:52:47Z",
            "F": 4,
            "M": 51,
            "FX": 0,
            "MX": 0,
            "X": 0,
            "NB": 0,
            "+": 0,
            "?": 0,
            "-": 5478
        }
    ],
    "sources": [
        {
            "x": "2022-02-02T06:54:45Z",
            "wikidata": 1150,
            "csv": 0,
            "config": 0,
            "-": 4440
        },
        {
            "x": "2021-12-02T06:53:10Z",
            "wikidata": 1150,
            "csv": 0,
            "config": 0,
            "-": 4420
        },
        {
            "x": "2022-01-02T06:57:28Z",
            "wikidata": 1149,
            "csv": 0,
            "config": 0,
            "-": 4436
        },
        {
            "x": "2021-11-02T06:52:28Z",
            "wikidata": 1148,
            "csv": 0,
            "config": 0,
            "-": 4416
        },
        {
            "x": "2021-10-02T06:53:55Z",
            "wikidata": 1072,
            "csv": 0,
            "config": 0,
            "-": 4485
        },
        {
            "x": "2021-09-23T07:15:14Z",
            "wikidata": 1070,
            "csv": 0,
            "config": 0,
            "-": 4484
        },
        {
            "x": "2021-09-09T07:15:30Z",
            "wikidata": 895,
            "csv": 0,
            "config": 0,
            "-": 4655
        },
        {
            "x": "2021-09-02T07:15:55Z",
            "wikidata": 894,
            "csv": 0,
            "config": 0,
            "-": 4648
        },
        {
            "x": "2021-08-26T07:12:23Z",
            "wikidata": 408,
            "csv": 0,
            "config": 0,
            "-": 5124
        },
        {
            "x": "2021-08-19T07:10:11Z",
            "wikidata": 166,
            "csv": 0,
            "config": 0,
            "-": 5367
        },
        {
            "x": "2021-08-16T15:40:13Z",
            "wikidata": 133,
            "csv": 0,
            "config": 0,
            "-": 5400
        },
        {
            "x": "2021-08-15T16:52:47Z",
            "wikidata": 109,
            "csv": 0,
            "config": 0,
            "-": 5424
        }
    ]
}