{
    "statistics": [
        {
            "x": 31000,
            "F": 19,
            "M": 102,
            "FX": 0,
            "MX": 0,
            "X": 0,
            "NB": 0,
            "+": 1,
            "?": 0,
            "-": 1442
        },
        {
            "x": 30000,
            "F": 19,
            "M": 102,
            "FX": 0,
            "MX": 0,
            "X": 0,
            "NB": 0,
            "+": 1,
            "?": 0,
            "-": 1442
        },
        {
            "x": 29000,
            "F": 20,
            "M": 107,
            "FX": 0,
            "MX": 0,
            "X": 0,
            "NB": 0,
            "+": 1,
            "?": 0,
            "-": 1436
        },
        {
            "x": 28000,
            "F": 20,
            "M": 107,
            "FX": 0,
            "MX": 0,
            "X": 0,
            "NB": 0,
            "+": 1,
            "?": 0,
            "-": 1436
        },
        {
            "x": 27000,
            "F": 20,
            "M": 107,
            "FX": 0,
            "MX": 0,
            "X": 0,
            "NB": 0,
            "+": 1,
            "?": 0,
            "-": 1436
        },
        {
            "x": 26000,
            "F": 20,
            "M": 107,
            "FX": 0,
            "MX": 0,
            "X": 0,
            "NB": 0,
            "+": 1,
            "?": 0,
            "-": 1436
        },
        {
            "x": 25000,
            "F": 20,
            "M": 107,
            "FX": 0,
            "MX": 0,
            "X": 0,
            "NB": 0,
            "+": 1,
            "?": 0,
            "-": 1439
        },
        {
            "x": 24000,
            "F": 20,
            "M": 107,
            "FX": 0,
            "MX": 0,
            "X": 0,
            "NB": 0,
            "+": 1,
            "?": 0,
            "-": 1439
        },
        {
            "x": 23000,
            "F": 20,
            "M": 107,
            "FX": 0,
            "MX": 0,
            "X": 0,
            "NB": 0,
            "+": 1,
            "?": 0,
            "-": 1440
        },
        {
            "x": 22000,
            "F": 20,
            "M": 107,
            "FX": 0,
            "MX": 0,
            "X": 0,
            "NB": 0,
            "+": 1,
            "?": 0,
            "-": 1440
        },
        {
            "x": 21000,
            "F": 20,
            "M": 107,
            "FX": 0,
            "MX": 0,
            "X": 0,
            "NB": 0,
            "+": 1,
            "?": 0,
            "-": 1438
        },
        {
            "x": 20000,
            "F": 20,
            "M": 107,
            "FX": 0,
            "MX": 0,
            "X": 0,
            "NB": 0,
            "+": 1,
            "?": 0,
            "-": 1438
        },
        {
            "x": 19000,
            "F": 20,
            "M": 107,
            "FX": 0,
            "MX": 0,
            "X": 0,
            "NB": 0,
            "+": 1,
            "?": 0,
            "-": 1437
        },
        {
            "x": 18000,
            "F": 20,
            "M": 107,
            "FX": 0,
            "MX": 0,
            "X": 0,
            "NB": 0,
            "+": 1,
            "?": 0,
            "-": 1438
        },
        {
            "x": 17000,
            "F": 20,
            "M": 107,
            "FX": 0,
            "MX": 0,
            "X": 0,
            "NB": 0,
            "+": 1,
            "?": 0,
            "-": 1438
        },
        {
            "x": 16000,
            "F": 20,
            "M": 107,
            "FX": 0,
            "MX": 0,
            "X": 0,
            "NB": 0,
            "+": 1,
            "?": 0,
            "-": 1438
        },
        {
            "x": 15000,
            "F": 20,
            "M": 107,
            "FX": 0,
            "MX": 0,
            "X": 0,
            "NB": 0,
            "+": 1,
            "?": 0,
            "-": 1439
        },
        {
            "x": 14000,
            "F": 19,
            "M": 123,
            "FX": 0,
            "MX": 0,
            "X": 0,
            "NB": 0,
            "+": 1,
            "?": 0,
            "-": 1422
        },
        {
            "x": 13000,
            "F": 19,
            "M": 124,
            "FX": 0,
            "MX": 0,
            "X": 0,
            "NB": 0,
            "+": 1,
            "?": 0,
            "-": 1422
        },
        {
            "x": 12000,
            "F": 19,
            "M": 124,
            "FX": 0,
            "MX": 0,
            "X": 0,
            "NB": 0,
            "+": 1,
            "?": 0,
            "-": 1422
        },
        {
            "x": 11000,
            "F": 19,
            "M": 126,
            "FX": 0,
            "MX": 0,
            "X": 0,
            "NB": 0,
            "+": 1,
            "?": 0,
            "-": 1420
        },
        {
            "x": 10000,
            "F": 17,
            "M": 91,
            "FX": 0,
            "MX": 0,
            "X": 0,
            "+": 0,
            "?": 0,
            "-": 1453
        },
        {
            "x": 9000,
            "F": 17,
            "M": 95,
            "FX": 0,
            "MX": 0,
            "X": 0,
            "+": 0,
            "?": 0,
            "-": 1450
        },
        {
            "x": 8000,
            "F": 18,
            "M": 98,
            "FX": 0,
            "MX": 0,
            "X": 0,
            "+": 1,
            "?": 0,
            "-": 1449
        },
        {
            "x": 7000,
            "F": 18,
            "M": 102,
            "FX": 0,
            "MX": 0,
            "X": 0,
            "+": 1,
            "?": 0,
            "-": 1446
        },
        {
            "x": 6000,
            "F": 19,
            "M": 102,
            "FX": 0,
            "MX": 0,
            "X": 0,
            "+": 1,
            "?": 0,
            "-": 1445
        },
        {
            "x": 5000,
            "F": 19,
            "M": 102,
            "FX": 0,
            "MX": 0,
            "X": 0,
            "+": 1,
            "?": 0,
            "-": 1450
        },
        {
            "x": 4000,
            "F": 19,
            "M": 102,
            "FX": 0,
            "MX": 0,
            "X": 0,
            "+": 1,
            "?": 0,
            "-": 1449
        },
        {
            "x": 3000,
            "F": 19,
            "M": 102,
            "FX": 0,
            "MX": 0,
            "X": 0,
            "+": 1,
            "?": 0,
            "-": 1452
        },
        {
            "x": 2000,
            "F": 19,
            "M": 102,
            "FX": 0,
            "MX": 0,
            "X": 0,
            "+": 1,
            "?": 0,
            "-": 1453
        },
        {
            "x": 1000,
            "F": 19,
            "M": 102,
            "FX": 0,
            "MX": 0,
            "X": 0,
            "NB": 0,
            "+": 1,
            "?": 0,
            "-": 1453
        },
        {
            "x": 0,
            "F": 19,
            "M": 102,
            "FX": 0,
            "MX": 0,
            "X": 0,
            "NB": 0,
            "+": 1,
            "?": 0,
            "-": 1442
        }
    ],
    "sources": [
        {
            "x": 23000,
            "wikidata": 169,
            "csv": 0,
            "config": 0,
            "event": 0,
            "-": 1395
        },
        {
            "x": 22000,
            "wikidata": 169,
            "csv": 0,
            "config": 0,
            "event": 0,
            "-": 1395
        },
        {
            "x": 21000,
            "wikidata": 128,
            "csv": 0,
            "config": 0,
            "-": 1436
        },
        {
            "x": 20000,
            "wikidata": 185,
            "csv": 0,
            "config": 0,
            "-": 1379
        },
        {
            "x": 19000,
            "wikidata": 185,
            "csv": 0,
            "config": 0,
            "-": 1379
        },
        {
            "x": 18000,
            "wikidata": 185,
            "csv": 0,
            "config": 0,
            "-": 1379
        },
        {
            "x": 17000,
            "wikidata": 185,
            "csv": 0,
            "config": 0,
            "-": 1382
        },
        {
            "x": 16000,
            "wikidata": 185,
            "csv": 0,
            "config": 0,
            "-": 1382
        },
        {
            "x": 15000,
            "wikidata": 186,
            "csv": 0,
            "config": 0,
            "-": 1382
        },
        {
            "x": 14000,
            "wikidata": 186,
            "csv": 0,
            "config": 0,
            "-": 1382
        },
        {
            "x": 13000,
            "wikidata": 186,
            "csv": 0,
            "config": 0,
            "-": 1380
        },
        {
            "x": 12000,
            "wikidata": 186,
            "csv": 0,
            "config": 0,
            "-": 1380
        },
        {
            "x": 11000,
            "wikidata": 186,
            "csv": 0,
            "config": 0,
            "-": 1379
        },
        {
            "x": 10000,
            "wikidata": 186,
            "csv": 0,
            "config": 0,
            "-": 1380
        },
        {
            "x": 9000,
            "wikidata": 186,
            "csv": 0,
            "config": 0,
            "-": 1380
        },
        {
            "x": 8000,
            "wikidata": 186,
            "csv": 0,
            "config": 0,
            "-": 1380
        },
        {
            "x": 7000,
            "wikidata": 186,
            "csv": 0,
            "config": 0,
            "-": 1381
        },
        {
            "x": 6000,
            "wikidata": 216,
            "csv": 0,
            "config": 0,
            "-": 1349
        },
        {
            "x": 5000,
            "wikidata": 217,
            "csv": 0,
            "config": 0,
            "-": 1349
        },
        {
            "x": 4000,
            "wikidata": 217,
            "csv": 0,
            "config": 0,
            "-": 1349
        },
        {
            "x": 3000,
            "wikidata": 219,
            "csv": 0,
            "config": 0,
            "-": 1347
        },
        {
            "x": 2000,
            "wikidata": 168,
            "config": 0,
            "event": 0,
            "-": 1407
        },
        {
            "x": 1000,
            "wikidata": 169,
            "config": 0,
            "event": 0,
            "-": 1395
        },
        {
            "x": 0,
            "wikidata": 169,
            "csv": 0,
            "config": 0,
            "event": 0,
            "-": 1395
        }
    ]
}